git_gerp.py
git_gerp-0.1.1.dist-info/METADATA
git_gerp-0.1.1.dist-info/RECORD
git_gerp-0.1.1.dist-info/WHEEL
git_gerp-0.1.1.dist-info/entry_points.txt
git_gerp-0.1.1.dist-info/top_level.txt
