Metadata-Version: 2.1
Name: git-gerp
Version: 0.1.1
Summary: git grep wrapper for arguments re-ordering, that can use options after filenames
Home-page: https://github.com/htaketani/git-gerp
Author: htaketani
Author-email: h.taketani@gmail.com
License: MIT
Platform: UNKNOWN
Classifier: Development Status :: 4 - Beta
Classifier: Environment :: Console
Classifier: Intended Audience :: Developers
Classifier: License :: OSI Approved :: MIT License
Classifier: Operating System :: OS Independent
Classifier: Programming Language :: Python :: 2
Classifier: Programming Language :: Python :: 3
Classifier: Topic :: Software Development :: Version Control
Classifier: Topic :: Utilities
